cogents_browser_use-0.1.1.dist-info/licenses/LICENSE
cogents_bu/__init__.py
cogents_bu/config.py
cogents_bu/exceptions.py
cogents_bu/llm_adapter.py
cogents_bu/logging_config.py
cogents_bu/observability.py
cogents_bu/utils.py
cogents_bu/agent/gif.py
cogents_bu/agent/prompts.py
cogents_bu/agent/service.py
cogents_bu/agent/views.py
cogents_bu/agent/message_manager/service.py
cogents_bu/agent/message_manager/utils.py
cogents_bu/agent/message_manager/views.py
cogents_bu/browser/__init__.py
cogents_bu/browser/events.py
cogents_bu/browser/profile.py
cogents_bu/browser/python_highlights.py
cogents_bu/browser/session.py
cogents_bu/browser/views.py
cogents_bu/browser/watchdog_base.py
cogents_bu/browser/watchdogs/__init__.py
cogents_bu/browser/watchdogs/aboutblank_watchdog.py
cogents_bu/browser/watchdogs/crash_watchdog.py
cogents_bu/browser/watchdogs/default_action_watchdog.py
cogents_bu/browser/watchdogs/dom_watchdog.py
cogents_bu/browser/watchdogs/downloads_watchdog.py
cogents_bu/browser/watchdogs/local_browser_watchdog.py
cogents_bu/browser/watchdogs/permissions_watchdog.py
cogents_bu/browser/watchdogs/popups_watchdog.py
cogents_bu/browser/watchdogs/screenshot_watchdog.py
cogents_bu/browser/watchdogs/security_watchdog.py
cogents_bu/browser/watchdogs/storage_state_watchdog.py
cogents_bu/controller/__init__.py
cogents_bu/dom/enhanced_snapshot.py
cogents_bu/dom/service.py
cogents_bu/dom/utils.py
cogents_bu/dom/views.py
cogents_bu/dom/serializer/clickable_elements.py
cogents_bu/dom/serializer/serializer.py
cogents_bu/filesystem/__init__.py
cogents_bu/filesystem/file_system.py
cogents_bu/integrations/gmail/__init__.py
cogents_bu/integrations/gmail/actions.py
cogents_bu/integrations/gmail/service.py
cogents_bu/mcp/__init__.py
cogents_bu/mcp/__main__.py
cogents_bu/mcp/client.py
cogents_bu/mcp/controller.py
cogents_bu/mcp/server.py
cogents_bu/screenshots/__init__.py
cogents_bu/screenshots/service.py
cogents_bu/tools/service.py
cogents_bu/tools/views.py
cogents_bu/tools/registry/service.py
cogents_bu/tools/registry/views.py
cogents_browser_use-0.1.1.dist-info/METADATA
cogents_browser_use-0.1.1.dist-info/WHEEL
cogents_browser_use-0.1.1.dist-info/top_level.txt
cogents_browser_use-0.1.1.dist-info/RECORD
